setup.py
django_transplant.egg-info/PKG-INFO
django_transplant.egg-info/SOURCES.txt
django_transplant.egg-info/dependency_links.txt
django_transplant.egg-info/requires.txt
django_transplant.egg-info/top_level.txt
transplant/__init__.py
transplant/forms.py
transplant/models.py
transplant/settings.py
transplant/surgeons.py
transplant/surgery.py
transplant/urls.py
transplant/views.py
transplant/tests/__init__.py
transplant/tests/models.py
transplant/tests/surgeons.py
transplant/tests/tests.py