Metadata-Version: 1.1
Name: django-transplant
Version: 0.0.2
Summary: Automated merges of User accounts.
Home-page: https://github.com/lolek09/django-transplant
Author: Karol Majta
Author-email: karolmajta@gmail.com
License: BSD
Keywords: django,user,account,merge
Platform: UNKNOWN
Classifier: Framework :: Django
Classifier: Development Status :: 4 - Beta
Classifier: Topic :: Internet
Classifier: License :: OSI Approved :: BSD License
Classifier: Intended Audience :: Developers
Classifier: Environment :: Web Environment
Classifier: Programming Language :: Python :: 2.7
